rapidy/__init__.py
rapidy/_base_exceptions.py
rapidy/_client_errors.py
rapidy/annotation_checkers.py
rapidy/constants.py
rapidy/depends.py
rapidy/encoders.py
rapidy/endpoint_handlers/__init__.py
rapidy/endpoint_handlers/attr_containers.py
rapidy/endpoint_handlers/attr_extractor.py
rapidy/endpoint_handlers/http/__init__.py
rapidy/endpoint_handlers/http/annotation_checkers.py
rapidy/endpoint_handlers/http/attr_containers.py
rapidy/endpoint_handlers/http/attrs_extractor.py
rapidy/endpoint_handlers/http/controller.py
rapidy/endpoint_handlers/http/fields.py
rapidy/endpoint_handlers/http/handlers.py
rapidy/endpoint_handlers/http/request/__init__.py
rapidy/endpoint_handlers/http/request/data_extractors.py
rapidy/endpoint_handlers/http/request/data_validators.py
rapidy/endpoint_handlers/validation.py
rapidy/enums.py
rapidy/fields/__init__.py
rapidy/fields/field_info.py
rapidy/fields/model_fields.py
rapidy/http.py
rapidy/lifespan.py
rapidy/mypy/__init__.py
rapidy/mypy/_api_errors.py
rapidy/mypy/_type_helpers.py
rapidy/mypy/_version.py
rapidy/mypy/plugin.py
rapidy/parameters/__init__.py
rapidy/parameters/http.py
rapidy/py.typed
rapidy/routing/__init__.py
rapidy/routing/http/__init__.py
rapidy/routing/http/base.py
rapidy/routing/http/helper_types.py
rapidy/routing/http/routers.py
rapidy/streams.py
rapidy/typedefs.py
rapidy/version.py
rapidy/web.py
rapidy/web_app.py
rapidy/web_exceptions.py
rapidy/web_middlewares.py
rapidy/web_request.py
rapidy/web_response.py
rapidy/web_routedef.py
rapidy/web_urldispatcher.py
rapidy-1.1.2.dist-info/LICENSE
rapidy-1.1.2.dist-info/METADATA
rapidy-1.1.2.dist-info/WHEEL
rapidy-1.1.2.dist-info/RECORD
