Metadata-Version: 2.1
Name: rAPIdy
Version: 1.1.2
Summary: rAPIdy - a fast, lightweight, and modern asynchronous web framework powered by aiohttp and pydantic.
License: MIT
Keywords: rAPIdy,aiohttp,pydantic,http,server,client,api,fast,http server,Daniil Grois,Lev Zaplatin,Nikita Tolstoy
Author: Daniil Grois
Author-email: daniil.grois@gmail.com
Maintainer: Daniil Grois
Maintainer-email: daniil.grois@gmail.com
Requires-Python: >=3.10
Classifier: Environment :: Web Environment
Classifier: Framework :: AsyncIO
Classifier: Intended Audience :: Developers
Classifier: Intended Audience :: Information Technology
Classifier: Intended Audience :: System Administrators
Classifier: License :: OSI Approved :: MIT License
Classifier: Operating System :: OS Independent
Classifier: Programming Language :: Python
Classifier: Programming Language :: Python :: 3
Classifier: Programming Language :: Python :: 3.10
Classifier: Programming Language :: Python :: 3.11
Classifier: Programming Language :: Python :: 3.12
Classifier: Programming Language :: Python :: 3 :: Only
Classifier: Programming Language :: Python :: 3.13
Classifier: Topic :: Internet
Classifier: Topic :: Internet :: WWW/HTTP
Classifier: Topic :: Software Development
Classifier: Topic :: Software Development :: Libraries
Classifier: Topic :: Software Development :: Libraries :: Python Modules
Classifier: Typing :: Typed
Requires-Dist: aiohttp (>=3.10.0,!=3.11.0,!=3.11.1,!=3.11.2)
Requires-Dist: dishka (>=1.5.3,<2.0.0)
Requires-Dist: pydantic (>=1.7.4,!=1.8,!=1.8.1,!=1.8.2,!=2.0.0,!=2.0.1,!=2.1.0,<3.0.0)
